scippneutron/__init__.py
scippneutron/beamline_components.py
scippneutron/instrument_view.py
scippneutron/logging.py
scippneutron/mantid.py
scippneutron/masking.py
scippneutron/py.typed
scippneutron/_html_repr/__init__.py
scippneutron/_html_repr/_disk_chopper_repr.py
scippneutron/_html_repr/_resources.py
scippneutron/_html_repr/styles/__init__.py
scippneutron/_html_repr/styles/disk_chopper.css
scippneutron/_html_repr/templates/__init__.py
scippneutron/_html_repr/templates/disk_chopper_repr.html.template
scippneutron/_utils/__init__.py
scippneutron/absorption/__init__.py
scippneutron/absorption/base.py
scippneutron/absorption/cylinder.py
scippneutron/absorption/material.py
scippneutron/absorption/quadratures.py
scippneutron/absorption/types.py
scippneutron/atoms/__init__.py
scippneutron/atoms/atomic_masses.csv
scippneutron/atoms/atomic_weights.csv
scippneutron/atoms/scattering_parameters.csv
scippneutron/chopper/__init__.py
scippneutron/chopper/__init__.pyi
scippneutron/chopper/_svg.py
scippneutron/chopper/disk_chopper.py
scippneutron/chopper/filtering.py
scippneutron/chopper/nexus_chopper.py
scippneutron/conversion/__init__.py
scippneutron/conversion/__init__.pyi
scippneutron/conversion/beamline.py
scippneutron/conversion/tof.py
scippneutron/conversion/graph/__init__.py
scippneutron/conversion/graph/__init__.pyi
scippneutron/conversion/graph/beamline.py
scippneutron/conversion/graph/tof.py
scippneutron/core/__init__.py
scippneutron/core/__init__.pyi
scippneutron/core/conversions.py
scippneutron/data/__init__.py
scippneutron/data/_chopper_mockup.py
scippneutron/io/__init__.py
scippneutron/io/__init__.pyi
scippneutron/io/_files.py
scippneutron/io/cif.py
scippneutron/io/xye.py
scippneutron/io/sqw/__init__.py
scippneutron/io/sqw/_build.py
scippneutron/io/sqw/_bytes.py
scippneutron/io/sqw/_ir.py
scippneutron/io/sqw/_low_level_io.py
scippneutron/io/sqw/_models.py
scippneutron/io/sqw/_read_write.py
scippneutron/io/sqw/_sqw.py
scippneutron/metadata/__init__.py
scippneutron-25.7.0.dist-info/licenses/LICENSE
scippneutron-25.7.0.dist-info/METADATA
scippneutron-25.7.0.dist-info/WHEEL
scippneutron-25.7.0.dist-info/top_level.txt
scippneutron-25.7.0.dist-info/RECORD
